README
setup.py
bin/mkschroot
mkschroot/__init__.py
mkschroot/chroot.py
mkschroot.egg-info/PKG-INFO
mkschroot.egg-info/SOURCES.txt
mkschroot.egg-info/dependency_links.txt
mkschroot.egg-info/requires.txt
mkschroot.egg-info/top_level.txt