Metadata-Version: 1.1
Name: mkschroot
Version: 0.3.4
Summary: A simple script for making schroot environments from a JSON configuration file
Home-page: https://github.com/KayEss/mkschroot
Author: Kirit Saelensminde
Author-email: kirit@felspar.com
License: Boost Software License - Version 1.0 - August 17th, 2003
Keywords: chroot debian devops
Platform: UNKNOWN
Classifier: Development Status :: 4 - Beta
Classifier: Intended Audience :: System Administrators
Classifier: Operating System :: POSIX :: Linux
Classifier: Topic :: System :: Systems Administration
Classifier: Programming Language :: Python
Classifier: License :: OSI Approved
